{
    "document_info": {
        "document_status": "PROFORMA INVOICE",
        "copy_name": "SGS REF 1 SQ/SM/090-2026"
    },
    "parties": {
        "shipper": {
            "name": "SGB Testing & Control Services Singapore Pte Ltd",
            "address": "30 Boon Lay Way, #03-01 Singapore 609957",
            "phone": "+65 6379 0111",
            "fax": "+65 6779 5805"
        },
        "consignee": {
            "name": "THE SHELL COMPANY OF THAILAND LTD.",
            "address": "SHELL HOUSE, 10 SOONTHORNKOSA RD., KLONGTOEY, BANGKOK, 10110, THAILAND.",
            "phone": "+66 955-942-545"
        },
        "issuing_agent": {
            "name": "SGB Testing & Control Services Singapore Pte Ltd",
            "city": "Singapore"
        }
    },
    "routing_and_destination": {
        "routing": [
            {
                "to": "THE SHELL COMPANY OF THAILAND LTD.",
                "by_carrier": "SGB Testing & Control Services Singapore Pte Ltd"
            }
        ],
        "destination_airport": null
    },
    "declaration": {
        "currency": "USD",
        "weight_valuation_charge": "AS ARRANGED",
        "declared_value_for_customs": "USD 20.00"
    },
    "cargo_details": {
        "dimensions": [
            "20 X 1 KG"
        ],
        "weight_unit": "KG",
        "total_weight_charge": "USD 20.00",
        "total_volume_mc": null
    },
    "handling_information": {
        "special_notes": "The goods mentioned above is supplied free-of charge to the consignee as sample for testing purposes only and not for commercial use; and that no payment in any form will be made for this / these good(s) at any time. Sample invoices are given for Customs purpose with No Commercial Value and is not for sale."
    },
    "accounting_and_charges": {
        "freight_prepaid": [
            "TONG SU QIN",
            "NATURAL RESOURCES",
            "OIL, GAS & CHEMICAL COMMODITIES",
            "(ON BEHALF OF SHELL INTERNATIONAL EASTERN COMPANY)"
        ],
        "other_charges_breakdown": {
            "other_charges": null,
            "currency": null,
            "amount": null
        },
        "total_prepaid_summary": {
            "total_other_charges_due_agent": null,
            "grand_total": "USD 20.00"
        }
    },
    "execution": {
        "carrier_signature_code": null
    }
}